{
    "uuids": {
        "phone_id": "87e43ce0-9e35-4711-b4f4-506427cf41f7",
        "uuid": "5bfc88f4-e7cb-49f5-a993-60e75c8eba57",
        "client_session_id": "a3b2cea1-9174-45a7-918e-96f621925975",
        "advertising_id": "9b834516-16c1-4384-b46c-1b2b79f25039",
        "android_device_id": "android-f4ec51d7e8b2dbaf",
        "request_id": "205d6e3f-7e64-4350-811b-b7464decf501",
        "tray_session_id": "3a428115-0aa7-45d8-a714-1f11018903f9"
    },
    "mid": "ZoWSYgABAAE4Msei_Zr3Iynhw3Rq",
    "ig_u_rur": null,
    "ig_www_claim": null,
    "authorization_data": {
        "ds_user_id": "67090393409",
        "sessionid": "67090393409%3A6KkaLhCSJwayOh%3A16%3AAYcLpyrTxsbFO_AgdFpgdHQFjgnUdmu_dsnI711ztQ"
    },
    "cookies": {},
    "last_login": 1720029804.691424,
    "device_settings": {
        "app_version": "269.0.0.18.75",
        "android_version": 26,
        "android_release": "8.0.0",
        "dpi": "480dpi",
        "resolution": "1080x1920",
        "manufacturer": "OnePlus",
        "device": "devitron",
        "model": "6T Dev",
        "cpu": "qcom",
        "version_code": "314665256"
    },
    "user_agent": "Instagram 269.0.0.18.75 Android (26/8.0.0; 480dpi; 1080x1920; OnePlus; 6T Dev; devitron; qcom; en_US; 314665256)",
    "country": "US",
    "country_code": 1,
    "locale": "en_US",
    "timezone_offset": -14400
}